goodenoughfor/__init__.py
GoodEnoughFor-0.0.0a0.dist-info/LICENSE.txt
GoodEnoughFor-0.0.0a0.dist-info/METADATA
GoodEnoughFor-0.0.0a0.dist-info/WHEEL
GoodEnoughFor-0.0.0a0.dist-info/top_level.txt
GoodEnoughFor-0.0.0a0.dist-info/RECORD
